LICENSE.txt
MANIFEST.in
README.rst
requirements.core.txt
requirements.txt
setup.py
core_schema_viewer_app/__init__.py
core_schema_viewer_app/admin.py
core_schema_viewer_app/apps.py
core_schema_viewer_app/discover.py
core_schema_viewer_app/menus.py
core_schema_viewer_app/models.py
core_schema_viewer_app/settings.py
core_schema_viewer_app/tasks.py
core_schema_viewer_app/urls.py
core_schema_viewer_app.egg-info/PKG-INFO
core_schema_viewer_app.egg-info/SOURCES.txt
core_schema_viewer_app.egg-info/dependency_links.txt
core_schema_viewer_app.egg-info/requires.txt
core_schema_viewer_app.egg-info/top_level.txt
core_schema_viewer_app/components/__init__.py
core_schema_viewer_app/components/sandbox_data_structure/__init__.py
core_schema_viewer_app/components/sandbox_data_structure/api.py
core_schema_viewer_app/components/sandbox_data_structure/models.py
core_schema_viewer_app/components/template_schema_viewer/__init__.py
core_schema_viewer_app/components/template_schema_viewer/api.py
core_schema_viewer_app/components/template_schema_viewer/models.py
core_schema_viewer_app/components/template_schema_viewer/watch.py
core_schema_viewer_app/permissions/__init__.py
core_schema_viewer_app/permissions/discover.py
core_schema_viewer_app/permissions/rights.py
core_schema_viewer_app/static/core_schema_viewer_app/admin/list/schema_viewer.js
core_schema_viewer_app/static/core_schema_viewer_app/admin/list/schema_viewer.raw.js
core_schema_viewer_app/static/core_schema_viewer_app/user/css/index.css
core_schema_viewer_app/static/core_schema_viewer_app/user/css/xsd_form.css
core_schema_viewer_app/static/core_schema_viewer_app/user/img/oxygen_logo.png
core_schema_viewer_app/static/core_schema_viewer_app/user/img/sandbox_logo.png
core_schema_viewer_app/static/core_schema_viewer_app/user/img/tabbed_logo.png
core_schema_viewer_app/static/core_schema_viewer_app/user/js/autosave.js
core_schema_viewer_app/static/core_schema_viewer_app/user/js/autosave.raw.js
core_schema_viewer_app/static/core_schema_viewer_app/user/js/buttons.raw.js
core_schema_viewer_app/static/core_schema_viewer_app/user/js/choice.raw.js
core_schema_viewer_app/static/core_schema_viewer_app/user/js/index.js
