Metadata-Version: 2.1
Name: core-schema-viewer-app
Version: 1.5.0
Summary: Schema Viewer app
Home-page: https://github.com/usnistgov/core_schema_viewer_app
Author: NIST IT Lab
Author-email: itl_inquiries@nist.gov
License: UNKNOWN
Platform: UNKNOWN
License-File: LICENSE.txt
